ddtrace_aiomisc/__init__.py
ddtrace_aiomisc/aiomisc.py
ddtrace_aiomisc-1.0.3.dist-info/LICENSE
ddtrace_aiomisc-1.0.3.dist-info/WHEEL
ddtrace_aiomisc-1.0.3.dist-info/METADATA
ddtrace_aiomisc-1.0.3.dist-info/RECORD
