Metadata-Version: 2.1
Name: ddtrace-aiomisc
Version: 1.0.3
Summary: ddtrace miscellaneous utils
Home-page: https://github.com/SandLabs/ddtrace-aiomisc
License: MIT
Author: m.shlyamov
Author-email: m.shlyamov@yandex.com
Requires-Python: >=3.6
Classifier: Intended Audience :: Developers
Classifier: License :: OSI Approved :: MIT License
Classifier: Natural Language :: English
Classifier: Operating System :: MacOS
Classifier: Operating System :: Microsoft :: Windows
Classifier: Operating System :: POSIX
Classifier: Operating System :: Unix
Classifier: Programming Language :: Python
Classifier: Programming Language :: Python :: 3
Classifier: Programming Language :: Python :: 3 :: Only
Classifier: Programming Language :: Python :: 3.6
Classifier: Programming Language :: Python :: 3.7
Classifier: Programming Language :: Python :: 3.8
Classifier: Topic :: Software Development
Classifier: Topic :: Software Development :: Libraries
Requires-Dist: ddtrace (>=0.31)
